MANIFEST.in
README.rst
requirements.txt
setup.cfg
setup.py
kotti_contenttypes/__init__.py
kotti_contenttypes/__init__.pyc
kotti_contenttypes/fanstatic.py
kotti_contenttypes/fanstatic.pyc
kotti_contenttypes/resources.py
kotti_contenttypes/resources.pyc
kotti_contenttypes.egg-info/PKG-INFO
kotti_contenttypes.egg-info/SOURCES.txt
kotti_contenttypes.egg-info/dependency_links.txt
kotti_contenttypes.egg-info/entry_points.txt
kotti_contenttypes.egg-info/not-zip-safe
kotti_contenttypes.egg-info/requires.txt
kotti_contenttypes.egg-info/top_level.txt
kotti_contenttypes/alembic/README
kotti_contenttypes/alembic/env.py
kotti_contenttypes/alembic/env.pyc
kotti_contenttypes/alembic/script.py.mako
kotti_contenttypes/alembic/versions/.gitkeep
kotti_contenttypes/locale/.gitkeep
kotti_contenttypes/static/folder.css
kotti_contenttypes/static/folder.js
kotti_contenttypes/static/list.min.js
kotti_contenttypes/static/scripts.js
kotti_contenttypes/static/scripts.min.js
kotti_contenttypes/static/styles.css
kotti_contenttypes/static/styles.min.css
kotti_contenttypes/static/ext/list.pagination.js/.bower.json
kotti_contenttypes/static/ext/list.pagination.js/Gruntfile.js
kotti_contenttypes/static/ext/list.pagination.js/Readme.md
kotti_contenttypes/static/ext/list.pagination.js/bower.json
kotti_contenttypes/static/ext/list.pagination.js/component.json
kotti_contenttypes/static/ext/list.pagination.js/index.js
kotti_contenttypes/static/ext/list.pagination.js/package.json
kotti_contenttypes/static/ext/list.pagination.js/dist/list.pagination.js
kotti_contenttypes/static/ext/list.pagination.js/dist/list.pagination.min.js
kotti_contenttypes/templates/folder.pt
kotti_contenttypes/tests/conftest.py
kotti_contenttypes/tests/test_functional.py
kotti_contenttypes/tests/test_resources.py
kotti_contenttypes/tests/test_view.py
kotti_contenttypes/views/__init__.py
kotti_contenttypes/views/__init__.pyc
kotti_contenttypes/views/edit.py
kotti_contenttypes/views/edit.pyc
kotti_contenttypes/views/view.py
kotti_contenttypes/views/view.pyc